{
  "_section_general": { "type": "hidden", "value": "──── GÉNÉRAL ────" },

  "language": {
    "type": "dropdown",
    "label": "Langue des messages",
    "value": "fr",
    "options": { "fr": "Français", "en": "English" }
  },

  "alertDuration": {
    "type": "number",
    "label": "Durée d'alerte (secondes)",
    "value": 7,
    "min": 2,
    "max": 30
  },

  "alertDelay": {
    "type": "number",
    "label": "Délai entre alertes (secondes)",
    "value": 0,
    "min": 0,
    "max": 10
  },

  "maxQueue": {
    "type": "number",
    "label": "Taille max de la file d'attente",
    "value": 10,
    "min": 1,
    "max": 50
  },

  "widgetWidth": {
    "type": "number",
    "label": "Largeur du widget (px)",
    "value": 680,
    "min": 300,
    "max": 1200
  },

  "position": {
    "type": "dropdown",
    "label": "Position du widget",
    "value": "bottom-center",
    "options": {
      "bottom-center": "Bas Centre",
      "bottom-left":   "Bas Gauche",
      "bottom-right":  "Bas Droite",
      "top-left":      "Haut Gauche",
      "top-center":    "Haut Centre",
      "top-right":     "Haut Droite",
      "center":        "Milieu"
    }
  },

  "_section_theme": { "type": "hidden", "value": "──── THÈME ────" },

  "theme": {
    "type": "dropdown",
    "label": "Thème",
    "value": "twitch",
    "options": {
      "twitch":  "Twitch Purple",
      "neon":    "Neon Cyan",
      "fire":    "Fire Orange",
      "rose":    "Rose Pastel",
      "minimal": "Minimal Blanc",
      "gold":    "Gold",
      "ocean":   "Ocean",
      "custom":  "Personnalisé"
    }
  },

  "accentColor": {
    "type": "colorpicker",
    "label": "Couleur accent (thème custom)",
    "value": "#9146ff"
  },

  "accentSecondary": {
    "type": "colorpicker",
    "label": "Couleur accent secondaire (thème custom)",
    "value": "#bf94ff"
  },

  "glowColor": {
    "type": "text",
    "label": "Couleur glow — rgba(...) (thème custom)",
    "value": "rgba(145,70,255,0.4)"
  },

  "bgColor": {
    "type": "text",
    "label": "Couleur fond — rgba(...) (thème custom)",
    "value": "rgba(15,10,30,0.95)"
  },

  "borderColor": {
    "type": "text",
    "label": "Couleur bordure — rgba(...) (thème custom)",
    "value": "rgba(145,70,255,0.5)"
  },

  "borderRadius": {
    "type": "number",
    "label": "Arrondi des coins (px)",
    "value": 16,
    "min": 0,
    "max": 40
  },

  "pulseGlow": {
    "type": "dropdown",
    "label": "Effet pulse glow",
    "value": "yes",
    "options": { "yes": "Oui", "no": "Non" }
  },

  "showParticles": {
    "type": "dropdown",
    "label": "Particules autour de l'icône",
    "value": "yes",
    "options": { "yes": "Oui", "no": "Non" }
  },

  "particleCount": {
    "type": "number",
    "label": "Nombre de particules",
    "value": 14,
    "min": 4,
    "max": 40
  },

  "showConfetti": {
    "type": "dropdown",
    "label": "Confetti (dons, giftsub, raid…)",
    "value": "no",
    "options": { "yes": "Oui", "no": "Non" }
  },

  "confettiBitsThreshold": {
    "type": "number",
    "label": "Seuil bits pour confetti",
    "value": 1000,
    "min": 1
  },

  "confettiOnFollow": {
    "type": "dropdown",
    "label": "Confetti sur Follower",
    "value": "no",
    "options": { "yes": "Oui", "no": "Non" }
  },

  "confettiOnSub": {
    "type": "dropdown",
    "label": "Confetti sur Sub / Resub",
    "value": "no",
    "options": { "yes": "Oui", "no": "Non" }
  },

  "showTypeBadge": {
    "type": "dropdown",
    "label": "Afficher badge type alerte",
    "value": "yes",
    "options": { "yes": "Oui", "no": "Non" }
  },

  "_section_font": { "type": "hidden", "value": "──── TEXTE ────" },

  "fontTitle": {
    "type": "dropdown",
    "label": "Police nom d'utilisateur",
    "value": "Montserrat",
    "options": {
      "Montserrat": "Montserrat",
      "Inter":      "Inter",
      "Orbitron":   "Orbitron",
      "Rajdhani":   "Rajdhani",
      "Poppins":    "Poppins"
    }
  },

  "fontMessage": {
    "type": "dropdown",
    "label": "Police message",
    "value": "Inter",
    "options": {
      "Inter":      "Inter",
      "Montserrat": "Montserrat",
      "Poppins":    "Poppins",
      "Rajdhani":   "Rajdhani"
    }
  },

  "fontSizeUsername": {
    "type": "number",
    "label": "Taille police nom (px)",
    "value": 22,
    "min": 12,
    "max": 40
  },

  "fontSizeMessage": {
    "type": "number",
    "label": "Taille police message (px)",
    "value": 14,
    "min": 10,
    "max": 24
  },

  "colorUsername": {
    "type": "colorpicker",
    "label": "Couleur nom d'utilisateur",
    "value": "#ffffff"
  },

  "colorMessage": {
    "type": "colorpicker",
    "label": "Couleur message",
    "value": "#dddddd"
  },

  "showAvatar": {
    "type": "dropdown",
    "label": "Afficher avatar (si dispo)",
    "value": "no",
    "options": { "yes": "Oui", "no": "Non" }
  },

  "_section_animation": { "type": "hidden", "value": "──── ANIMATION ────" },

  "animationIn": {
    "type": "dropdown",
    "label": "Animation d'entrée",
    "value": "slideup",
    "options": {
      "slideup":    "Slide Up",
      "slideleft":  "Slide Left",
      "slideright": "Slide Right",
      "zoom":       "Zoom",
      "bounce":     "Bounce",
      "flip":       "Flip",
      "fade":       "Fade"
    }
  },

  "animationOut": {
    "type": "dropdown",
    "label": "Animation de sortie",
    "value": "fade",
    "options": {
      "slideup":    "Slide Down",
      "slideleft":  "Slide Left Out",
      "slideright": "Slide Right Out",
      "zoom":       "Zoom Out",
      "bounce":     "Bounce Out",
      "flip":       "Flip Out",
      "fade":       "Fade"
    }
  },

  "shakeIcon": {
    "type": "dropdown",
    "label": "Secouer icône sur bits",
    "value": "yes",
    "options": { "yes": "Oui", "no": "Non" }
  },

  "_section_events": { "type": "hidden", "value": "──── ÉVÉNEMENTS ────" },

  "enableFollow": {
    "type": "dropdown",
    "label": "Alertes Followers",
    "value": "yes",
    "options": { "yes": "Oui", "no": "Non" }
  },

  "enableSub": {
    "type": "dropdown",
    "label": "Alertes Subs / Resubs / GiftSubs",
    "value": "yes",
    "options": { "yes": "Oui", "no": "Non" }
  },

  "enableBits": {
    "type": "dropdown",
    "label": "Alertes Bits / Cheers",
    "value": "yes",
    "options": { "yes": "Oui", "no": "Non" }
  },

  "enableTip": {
    "type": "dropdown",
    "label": "Alertes Donations (Tips)",
    "value": "yes",
    "options": { "yes": "Oui", "no": "Non" }
  },

  "enableRaid": {
    "type": "dropdown",
    "label": "Alertes Raids",
    "value": "yes",
    "options": { "yes": "Oui", "no": "Non" }
  },

  "enableHost": {
    "type": "dropdown",
    "label": "Alertes Hosts",
    "value": "yes",
    "options": { "yes": "Oui", "no": "Non" }
  },

  "minBits": {
    "type": "number",
    "label": "Montant minimum bits",
    "value": 1,
    "min": 1
  },

  "minTip": {
    "type": "number",
    "label": "Montant minimum donation",
    "value": 0,
    "min": 0
  },

  "currency": {
    "type": "text",
    "label": "Devise par défaut",
    "value": "€"
  },

  "_section_icons": { "type": "hidden", "value": "──── ICÔNES ────" },

  "iconFollow":  { "type": "text", "label": "Icône Follower",  "value": "💜" },
  "iconSub":     { "type": "text", "label": "Icône Sub",       "value": "⭐" },
  "iconResub":   { "type": "text", "label": "Icône Resub",     "value": "🔄" },
  "iconGiftSub": { "type": "text", "label": "Icône GiftSub",   "value": "🎁" },
  "iconBits":    { "type": "text", "label": "Icône Bits",      "value": "💎" },
  "iconTip":     { "type": "text", "label": "Icône Donation",  "value": "💰" },
  "iconRaid":    { "type": "text", "label": "Icône Raid",      "value": "⚔️" },
  "iconHost":    { "type": "text", "label": "Icône Host",      "value": "📡" },

  "_section_messages": { "type": "hidden", "value": "──── MESSAGES ────" },

  "msgFollow":  { "type": "text", "label": "Message Follower ({user})",              "value": "{user} te follow ! 💜" },
  "msgSub":     { "type": "text", "label": "Message Sub ({user})",                   "value": "{user} vient de sub !" },
  "msgResub":   { "type": "text", "label": "Message Resub ({user}, {months})",       "value": "{user} resub x{months} mois !" },
  "msgGiftSub": { "type": "text", "label": "Message GiftSub ({user}, {count})",      "value": "{user} offre {count} sub(s) !" },
  "msgBits":    { "type": "text", "label": "Message Bits ({user}, {bits})",          "value": "{user} envoie {bits} bits !" },
  "msgTip":     { "type": "text", "label": "Message Donation ({user}, {amount}, {currency})", "value": "{user} donne {amount}{currency} !" },
  "msgRaid":    { "type": "text", "label": "Message Raid ({user}, {count})",         "value": "{user} raid avec {count} raiders !" },
  "msgHost":    { "type": "text", "label": "Message Host ({user})",                  "value": "{user} host le stream !" },

  "_section_colors": { "type": "hidden", "value": "──── COULEURS PAR TYPE ────" },

  "colorFollow":  { "type": "colorpicker", "label": "Couleur Follower",  "value": "" },
  "colorSub":     { "type": "colorpicker", "label": "Couleur Sub",       "value": "" },
  "colorResub":   { "type": "colorpicker", "label": "Couleur Resub",     "value": "" },
  "colorGiftSub": { "type": "colorpicker", "label": "Couleur GiftSub",   "value": "" },
  "colorBits":    { "type": "colorpicker", "label": "Couleur Bits",      "value": "" },
  "colorTip":     { "type": "colorpicker", "label": "Couleur Donation",  "value": "" },
  "colorRaid":    { "type": "colorpicker", "label": "Couleur Raid",      "value": "" },
  "colorHost":    { "type": "colorpicker", "label": "Couleur Host",      "value": "" },

  "_section_sounds": { "type": "hidden", "value": "──── SONS ────" },

  "soundFollow":       { "type": "text",   "label": "Son Follower (URL)",         "value": "" },
  "soundVolumeFollow": { "type": "number", "label": "Volume Follower (0-1)",      "value": 0.7, "min": 0, "max": 1, "steps": 0.05 },
  "soundSub":          { "type": "text",   "label": "Son Sub (URL)",              "value": "" },
  "soundVolumeSub":    { "type": "number", "label": "Volume Sub (0-1)",           "value": 0.8, "min": 0, "max": 1, "steps": 0.05 },
  "soundResub":        { "type": "text",   "label": "Son Resub (URL)",            "value": "" },
  "soundVolumeResub":  { "type": "number", "label": "Volume Resub (0-1)",         "value": 0.8, "min": 0, "max": 1, "steps": 0.05 },
  "soundGiftSub":      { "type": "text",   "label": "Son GiftSub (URL)",          "value": "" },
  "soundVolumeGiftSub":{ "type": "number", "label": "Volume GiftSub (0-1)",       "value": 0.8, "min": 0, "max": 1, "steps": 0.05 },
  "soundBits":         { "type": "text",   "label": "Son Bits (URL)",             "value": "" },
  "soundVolumeBits":   { "type": "number", "label": "Volume Bits (0-1)",          "value": 0.75, "min": 0, "max": 1, "steps": 0.05 },
  "soundTip":          { "type": "text",   "label": "Son Donation (URL)",         "value": "" },
  "soundVolumeTip":    { "type": "number", "label": "Volume Donation (0-1)",      "value": 0.9, "min": 0, "max": 1, "steps": 0.05 },
  "soundRaid":         { "type": "text",   "label": "Son Raid (URL)",             "value": "" },
  "soundVolumeRaid":   { "type": "number", "label": "Volume Raid (0-1)",          "value": 0.8, "min": 0, "max": 1, "steps": 0.05 },
  "soundHost":         { "type": "text",   "label": "Son Host (URL)",             "value": "" },
  "soundVolumeHost":   { "type": "number", "label": "Volume Host (0-1)",          "value": 0.7, "min": 0, "max": 1, "steps": 0.05 }
}
